video_extract_audio_mcp/__init__.py
video_extract_audio_mcp/main.py
mcpcn_video_extract_audio_mcp-0.1.6.dist-info/METADATA
mcpcn_video_extract_audio_mcp-0.1.6.dist-info/WHEEL
mcpcn_video_extract_audio_mcp-0.1.6.dist-info/entry_points.txt
mcpcn_video_extract_audio_mcp-0.1.6.dist-info/RECORD
